<?xml version="1.0" ?>
<annotation>
<folder>VOC2007</folder>
<filename>228.jpg</filename>
<source>
<database>The VOC2007 Database</database>
<annotation>PASCAL VOC2007</annotation>
<image>flickr</image>
<flickrid>322409915</flickrid>
</source>
<size>
<width>2169</width>
<height>1969</height>
<depth>3</depth>
</size>
<segmented>0</segmented>
<object>
<name>ship</name>
<pose>Unspecified</pose>
<truncated>1</truncated>
<difficult>0</difficult>
<bndbox>
<xmin>287</xmin>
<ymin>94</ymin>
<xmax>304</xmax>
<ymax>117</ymax>
</bndbox>
</object>
<object>
<name>prefabricated-house</name>
<pose>Unspecified</pose>
<truncated>1</truncated>
<difficult>0</difficult>
<bndbox>
<xmin>263</xmin>
<ymin>165</ymin>
<xmax>294</xmax>
<ymax>198</ymax>
</bndbox>
</object>
<object>
<name>prefabricated-house</name>
<pose>Unspecified</pose>
<truncated>1</truncated>
<difficult>0</difficult>
<bndbox>
<xmin>215</xmin>
<ymin>326</ymin>
<xmax>239</xmax>
<ymax>368</ymax>
</bndbox>
</object>
<object>
<name>prefabricated-house</name>
<pose>Unspecified</pose>
<truncated>1</truncated>
<difficult>0</difficult>
<bndbox>
<xmin>184</xmin>
<ymin>535</ymin>
<xmax>216</xmax>
<ymax>573</ymax>
</bndbox>
</object>
<object>
<name>ship</name>
<pose>Unspecified</pose>
<truncated>1</truncated>
<difficult>0</difficult>
<bndbox>
<xmin>192</xmin>
<ymin>448</ymin>
<xmax>231</xmax>
<ymax>479</ymax>
</bndbox>
</object>
<object>
<name>ship</name>
<pose>Unspecified</pose>
<truncated>1</truncated>
<difficult>0</difficult>
<bndbox>
<xmin>276</xmin>
<ymin>435</ymin>
<xmax>303</xmax>
<ymax>452</ymax>
</bndbox>
</object>
<object>
<name>ship</name>
<pose>Unspecified</pose>
<truncated>1</truncated>
<difficult>0</difficult>
<bndbox>
<xmin>137</xmin>
<ymin>666</ymin>
<xmax>186</xmax>
<ymax>684</ymax>
</bndbox>
</object>
<object>
<name>prefabricated-house</name>
<pose>Unspecified</pose>
<truncated>1</truncated>
<difficult>0</difficult>
<bndbox>
<xmin>470</xmin>
<ymin>703</ymin>
<xmax>510</xmax>
<ymax>744</ymax>
</bndbox>
</object>
<object>
<name>prefabricated-house</name>
<pose>Unspecified</pose>
<truncated>1</truncated>
<difficult>0</difficult>
<bndbox>
<xmin>751</xmin>
<ymin>783</ymin>
<xmax>786</xmax>
<ymax>812</ymax>
</bndbox>
</object>
<object>
<name>prefabricated-house</name>
<pose>Unspecified</pose>
<truncated>1</truncated>
<difficult>0</difficult>
<bndbox>
<xmin>914</xmin>
<ymin>1031</ymin>
<xmax>943</xmax>
<ymax>1075</ymax>
</bndbox>
</object>
<object>
<name>prefabricated-house</name>
<pose>Unspecified</pose>
<truncated>1</truncated>
<difficult>0</difficult>
<bndbox>
<xmin>1005</xmin>
<ymin>1246</ymin>
<xmax>1048</xmax>
<ymax>1288</ymax>
</bndbox>
</object>
<object>
<name>prefabricated-house</name>
<pose>Unspecified</pose>
<truncated>1</truncated>
<difficult>0</difficult>
<bndbox>
<xmin>977</xmin>
<ymin>1356</ymin>
<xmax>1016</xmax>
<ymax>1395</ymax>
</bndbox>
</object>
<object>
<name>ship</name>
<pose>Unspecified</pose>
<truncated>1</truncated>
<difficult>0</difficult>
<bndbox>
<xmin>1083</xmin>
<ymin>1370</ymin>
<xmax>1098</xmax>
<ymax>1410</ymax>
</bndbox>
</object>
<object>
<name>prefabricated-house</name>
<pose>Unspecified</pose>
<truncated>1</truncated>
<difficult>0</difficult>
<bndbox>
<xmin>1136</xmin>
<ymin>1564</ymin>
<xmax>1175</xmax>
<ymax>1603</ymax>
</bndbox>
</object>
<object>
<name>prefabricated-house</name>
<pose>Unspecified</pose>
<truncated>1</truncated>
<difficult>0</difficult>
<bndbox>
<xmin>1248</xmin>
<ymin>1767</ymin>
<xmax>1285</xmax>
<ymax>1808</ymax>
</bndbox>
</object>
<object>
<name>prefabricated-house</name>
<pose>Unspecified</pose>
<truncated>1</truncated>
<difficult>0</difficult>
<bndbox>
<xmin>1337</xmin>
<ymin>1818</ymin>
<xmax>1371</xmax>
<ymax>1847</ymax>
</bndbox>
</object>
<object>
<name>prefabricated-house</name>
<pose>Unspecified</pose>
<truncated>1</truncated>
<difficult>0</difficult>
<bndbox>
<xmin>1588</xmin>
<ymin>1609</ymin>
<xmax>1607</xmax>
<ymax>1646</ymax>
</bndbox>
</object>
<object>
<name>prefabricated-house</name>
<pose>Unspecified</pose>
<truncated>1</truncated>
<difficult>0</difficult>
<bndbox>
<xmin>1550</xmin>
<ymin>1357</ymin>
<xmax>1582</xmax>
<ymax>1405</ymax>
</bndbox>
</object>
<object>
<name>building</name>
<pose>Unspecified</pose>
<truncated>1</truncated>
<difficult>0</difficult>
<bndbox>
<xmin>1571</xmin>
<ymin>1283</ymin>
<xmax>1590</xmax>
<ymax>1322</ymax>
</bndbox>
</object>
<object>
<name>ship</name>
<pose>Unspecified</pose>
<truncated>1</truncated>
<difficult>0</difficult>
<bndbox>
<xmin>1559</xmin>
<ymin>1137</ymin>
<xmax>1583</xmax>
<ymax>1186</ymax>
</bndbox>
</object>
<object>
<name>building</name>
<pose>Unspecified</pose>
<truncated>1</truncated>
<difficult>0</difficult>
<bndbox>
<xmin>1323</xmin>
<ymin>1009</ymin>
<xmax>1414</xmax>
<ymax>1079</ymax>
</bndbox>
</object>
<object>
<name>building</name>
<pose>Unspecified</pose>
<truncated>1</truncated>
<difficult>0</difficult>
<bndbox>
<xmin>1397</xmin>
<ymin>952</ymin>
<xmax>1492</xmax>
<ymax>1037</ymax>
</bndbox>
</object>
</annotation>
