<?xml version="1.0" ?>
<annotation>
<folder>VOC2007</folder>
<filename>630.jpg</filename>
<source>
<database>The VOC2007 Database</database>
<annotation>PASCAL VOC2007</annotation>
<image>flickr</image>
<flickrid>322409915</flickrid>
</source>
<size>
<width>1485</width>
<height>2515</height>
<depth>3</depth>
</size>
<segmented>0</segmented>
<object>
<name>building</name>
<pose>Unspecified</pose>
<truncated>1</truncated>
<difficult>0</difficult>
<bndbox>
<xmin>600</xmin>
<ymin>2251</ymin>
<xmax>727</xmax>
<ymax>2404</ymax>
</bndbox>
</object>
<object>
<name>building</name>
<pose>Unspecified</pose>
<truncated>1</truncated>
<difficult>0</difficult>
<bndbox>
<xmin>320</xmin>
<ymin>1955</ymin>
<xmax>538</xmax>
<ymax>2080</ymax>
</bndbox>
</object>
<object>
<name>building</name>
<pose>Unspecified</pose>
<truncated>1</truncated>
<difficult>0</difficult>
<bndbox>
<xmin>558</xmin>
<ymin>1839</ymin>
<xmax>704</xmax>
<ymax>1973</ymax>
</bndbox>
</object>
<object>
<name>building</name>
<pose>Unspecified</pose>
<truncated>1</truncated>
<difficult>0</difficult>
<bndbox>
<xmin>264</xmin>
<ymin>1747</ymin>
<xmax>499</xmax>
<ymax>1879</ymax>
</bndbox>
</object>
<object>
<name>building</name>
<pose>Unspecified</pose>
<truncated>1</truncated>
<difficult>0</difficult>
<bndbox>
<xmin>824</xmin>
<ymin>1940</ymin>
<xmax>1010</xmax>
<ymax>2059</ymax>
</bndbox>
</object>
<object>
<name>building</name>
<pose>Unspecified</pose>
<truncated>1</truncated>
<difficult>0</difficult>
<bndbox>
<xmin>585</xmin>
<ymin>1373</ymin>
<xmax>739</xmax>
<ymax>1581</ymax>
</bndbox>
</object>
<object>
<name>building</name>
<pose>Unspecified</pose>
<truncated>1</truncated>
<difficult>0</difficult>
<bndbox>
<xmin>765</xmin>
<ymin>1163</ymin>
<xmax>915</xmax>
<ymax>1289</ymax>
</bndbox>
</object>
<object>
<name>building</name>
<pose>Unspecified</pose>
<truncated>1</truncated>
<difficult>0</difficult>
<bndbox>
<xmin>556</xmin>
<ymin>674</ymin>
<xmax>724</xmax>
<ymax>879</ymax>
</bndbox>
</object>
<object>
<name>building</name>
<pose>Unspecified</pose>
<truncated>1</truncated>
<difficult>0</difficult>
<bndbox>
<xmin>581</xmin>
<ymin>340</ymin>
<xmax>734</xmax>
<ymax>488</ymax>
</bndbox>
</object>
<object>
<name>building</name>
<pose>Unspecified</pose>
<truncated>1</truncated>
<difficult>0</difficult>
<bndbox>
<xmin>672</xmin>
<ymin>198</ymin>
<xmax>759</xmax>
<ymax>319</ymax>
</bndbox>
</object>
<object>
<name>building</name>
<pose>Unspecified</pose>
<truncated>1</truncated>
<difficult>0</difficult>
<bndbox>
<xmin>744</xmin>
<ymin>607</ymin>
<xmax>859</xmax>
<ymax>724</ymax>
</bndbox>
</object>
<object>
<name>building</name>
<pose>Unspecified</pose>
<truncated>1</truncated>
<difficult>0</difficult>
<bndbox>
<xmin>752</xmin>
<ymin>726</ymin>
<xmax>861</xmax>
<ymax>827</ymax>
</bndbox>
</object>
<object>
<name>building</name>
<pose>Unspecified</pose>
<truncated>1</truncated>
<difficult>0</difficult>
<bndbox>
<xmin>925</xmin>
<ymin>753</ymin>
<xmax>1024</xmax>
<ymax>855</ymax>
</bndbox>
</object>
<object>
<name>building</name>
<pose>Unspecified</pose>
<truncated>1</truncated>
<difficult>0</difficult>
<bndbox>
<xmin>847</xmin>
<ymin>417</ymin>
<xmax>975</xmax>
<ymax>533</ymax>
</bndbox>
</object>
<object>
<name>building</name>
<pose>Unspecified</pose>
<truncated>1</truncated>
<difficult>0</difficult>
<bndbox>
<xmin>939</xmin>
<ymin>344</ymin>
<xmax>1020</xmax>
<ymax>463</ymax>
</bndbox>
</object>
<object>
<name>building</name>
<pose>Unspecified</pose>
<truncated>1</truncated>
<difficult>0</difficult>
<bndbox>
<xmin>946</xmin>
<ymin>585</ymin>
<xmax>1054</xmax>
<ymax>699</ymax>
</bndbox>
</object>
<object>
<name>building</name>
<pose>Unspecified</pose>
<truncated>1</truncated>
<difficult>0</difficult>
<bndbox>
<xmin>663</xmin>
<ymin>1901</ymin>
<xmax>713</xmax>
<ymax>1987</ymax>
</bndbox>
</object>
<object>
<name>building</name>
<pose>Unspecified</pose>
<truncated>1</truncated>
<difficult>0</difficult>
<bndbox>
<xmin>427</xmin>
<ymin>2029</ymin>
<xmax>512</xmax>
<ymax>2106</ymax>
</bndbox>
</object>
<object>
<name>building</name>
<pose>Unspecified</pose>
<truncated>1</truncated>
<difficult>1</difficult>
<bndbox>
<xmin>359</xmin>
<ymin>2079</ymin>
<xmax>479</xmax>
<ymax>2167</ymax>
</bndbox>
</object>
<object>
<name>building</name>
<pose>Unspecified</pose>
<truncated>1</truncated>
<difficult>0</difficult>
<bndbox>
<xmin>463</xmin>
<ymin>2083</ymin>
<xmax>561</xmax>
<ymax>2181</ymax>
</bndbox>
</object>
<object>
<name>building</name>
<pose>Unspecified</pose>
<truncated>1</truncated>
<difficult>0</difficult>
<bndbox>
<xmin>732</xmin>
<ymin>2314</ymin>
<xmax>812</xmax>
<ymax>2400</ymax>
</bndbox>
</object>
<object>
<name>building</name>
<pose>Unspecified</pose>
<truncated>1</truncated>
<difficult>0</difficult>
<bndbox>
<xmin>1052</xmin>
<ymin>1932</ymin>
<xmax>1116</xmax>
<ymax>2014</ymax>
</bndbox>
</object>
<object>
<name>building</name>
<pose>Unspecified</pose>
<truncated>1</truncated>
<difficult>0</difficult>
<bndbox>
<xmin>885</xmin>
<ymin>1814</ymin>
<xmax>1011</xmax>
<ymax>1931</ymax>
</bndbox>
</object>
<object>
<name>building</name>
<pose>Unspecified</pose>
<truncated>1</truncated>
<difficult>0</difficult>
<bndbox>
<xmin>831</xmin>
<ymin>1692</ymin>
<xmax>948</xmax>
<ymax>1808</ymax>
</bndbox>
</object>
<object>
<name>building</name>
<pose>Unspecified</pose>
<truncated>1</truncated>
<difficult>0</difficult>
<bndbox>
<xmin>570</xmin>
<ymin>987</ymin>
<xmax>681</xmax>
<ymax>1104</ymax>
</bndbox>
</object>
<object>
<name>building</name>
<pose>Unspecified</pose>
<truncated>1</truncated>
<difficult>0</difficult>
<bndbox>
<xmin>837</xmin>
<ymin>804</ymin>
<xmax>957</xmax>
<ymax>925</ymax>
</bndbox>
</object>
<object>
<name>building</name>
<pose>Unspecified</pose>
<truncated>1</truncated>
<difficult>0</difficult>
<bndbox>
<xmin>894</xmin>
<ymin>577</ymin>
<xmax>966</xmax>
<ymax>646</ymax>
</bndbox>
</object>
<object>
<name>building</name>
<pose>Unspecified</pose>
<truncated>1</truncated>
<difficult>0</difficult>
<bndbox>
<xmin>906</xmin>
<ymin>495</ymin>
<xmax>999</xmax>
<ymax>565</ymax>
</bndbox>
</object>
<object>
<name>building</name>
<pose>Unspecified</pose>
<truncated>1</truncated>
<difficult>0</difficult>
<bndbox>
<xmin>731</xmin>
<ymin>146</ymin>
<xmax>819</xmax>
<ymax>241</ymax>
</bndbox>
</object>
<object>
<name>building</name>
<pose>Unspecified</pose>
<truncated>1</truncated>
<difficult>0</difficult>
<bndbox>
<xmin>764</xmin>
<ymin>124</ymin>
<xmax>836</xmax>
<ymax>175</ymax>
</bndbox>
</object>
<object>
<name>building</name>
<pose>Unspecified</pose>
<truncated>1</truncated>
<difficult>0</difficult>
<bndbox>
<xmin>1003</xmin>
<ymin>331</ymin>
<xmax>1084</xmax>
<ymax>463</ymax>
</bndbox>
</object>
<object>
<name>building</name>
<pose>Unspecified</pose>
<truncated>1</truncated>
<difficult>0</difficult>
<bndbox>
<xmin>891</xmin>
<ymin>319</ymin>
<xmax>974</xmax>
<ymax>380</ymax>
</bndbox>
</object>
<object>
<name>building</name>
<pose>Unspecified</pose>
<truncated>1</truncated>
<difficult>0</difficult>
<bndbox>
<xmin>840</xmin>
<ymin>377</ymin>
<xmax>924</xmax>
<ymax>451</ymax>
</bndbox>
</object>
<object>
<name>building</name>
<pose>Unspecified</pose>
<truncated>1</truncated>
<difficult>0</difficult>
<bndbox>
<xmin>946</xmin>
<ymin>540</ymin>
<xmax>1023</xmax>
<ymax>602</ymax>
</bndbox>
</object>
<object>
<name>building</name>
<pose>Unspecified</pose>
<truncated>1</truncated>
<difficult>1</difficult>
<bndbox>
<xmin>694</xmin>
<ymin>938</ymin>
<xmax>803</xmax>
<ymax>1058</ymax>
</bndbox>
</object>
<object>
<name>prefabricated-house</name>
<pose>Unspecified</pose>
<truncated>1</truncated>
<difficult>0</difficult>
<bndbox>
<xmin>603</xmin>
<ymin>1520</ymin>
<xmax>630</xmax>
<ymax>1562</ymax>
</bndbox>
</object>
<object>
<name>building</name>
<pose>Unspecified</pose>
<truncated>1</truncated>
<difficult>0</difficult>
<bndbox>
<xmin>491</xmin>
<ymin>944</ymin>
<xmax>632</xmax>
<ymax>1042</ymax>
</bndbox>
</object>
<object>
<name>building</name>
<pose>Unspecified</pose>
<truncated>1</truncated>
<difficult>0</difficult>
<bndbox>
<xmin>742</xmin>
<ymin>476</ymin>
<xmax>893</xmax>
<ymax>591</ymax>
</bndbox>
</object>
<object>
<name>building</name>
<pose>Unspecified</pose>
<truncated>1</truncated>
<difficult>0</difficult>
<bndbox>
<xmin>1351</xmin>
<ymin>506</ymin>
<xmax>1485</xmax>
<ymax>589</ymax>
</bndbox>
</object>
<object>
<name>building</name>
<pose>Unspecified</pose>
<truncated>1</truncated>
<difficult>0</difficult>
<bndbox>
<xmin>1411</xmin>
<ymin>438</ymin>
<xmax>1476</xmax>
<ymax>514</ymax>
</bndbox>
</object>
<object>
<name>building</name>
<pose>Unspecified</pose>
<truncated>1</truncated>
<difficult>0</difficult>
<bndbox>
<xmin>1312</xmin>
<ymin>423</ymin>
<xmax>1406</xmax>
<ymax>508</ymax>
</bndbox>
</object>
<object>
<name>building</name>
<pose>Unspecified</pose>
<truncated>1</truncated>
<difficult>0</difficult>
<bndbox>
<xmin>1405</xmin>
<ymin>595</ymin>
<xmax>1485</xmax>
<ymax>683</ymax>
</bndbox>
</object>
<object>
<name>building</name>
<pose>Unspecified</pose>
<truncated>1</truncated>
<difficult>0</difficult>
<bndbox>
<xmin>467</xmin>
<ymin>774</ymin>
<xmax>592</xmax>
<ymax>881</ymax>
</bndbox>
</object>
</annotation>
